README.md
setup.py
tradeplot/__init__.py
tradeplot/basic.py
tradeplot/grammer.py
tradeplot/kline.py
tradeplot/main.py
tradeplot/trading.py
tradeplot.egg-info/PKG-INFO
tradeplot.egg-info/SOURCES.txt
tradeplot.egg-info/dependency_links.txt
tradeplot.egg-info/not-zip-safe
tradeplot.egg-info/requires.txt
tradeplot.egg-info/top_level.txt