Metadata-Version: 1.1
Name: tradeplot
Version: 0.3
Summary: use pyecharts to realize trading chart
Home-page: https://github.com/Yvictor/TradePlot
Author: YVictor
Author-email: yvictor3141@gmail.com
License: UNKNOWN
Platform: any
Classifier: Development Status :: 3 - Alpha
Classifier: Environment :: Console
Classifier: Intended Audience :: Developers
Classifier: Operating System :: POSIX
Classifier: Operating System :: MacOS
Classifier: Operating System :: Unix
Classifier: Operating System :: Microsoft :: Windows
Classifier: Programming Language :: Python :: 3
Classifier: Topic :: Software Development :: Libraries :: Python Modules
